TransportMaps/Defaults.py
TransportMaps/DerivativesChecks.py
TransportMaps/External.py
TransportMaps/FiniteDifference.py
TransportMaps/LaplaceApproximationRoutines.py
TransportMaps/MPI.py
TransportMaps/Misc.py
TransportMaps/ObjectBase.py
TransportMaps/Routines.py
TransportMaps/__init__.py
TransportMaps/_version.py
TransportMaps/Algorithms/__init__.py
TransportMaps/Algorithms/Adaptivity/KullbackLeiblerAdaptivity.py
TransportMaps/Algorithms/Adaptivity/RegressionAdaptivity.py
TransportMaps/Algorithms/Adaptivity/__init__.py
TransportMaps/Algorithms/DeepLazyMaps/DeepLazyMapFactories.py
TransportMaps/Algorithms/DeepLazyMaps/DeepLazyMapsConstructionBase.py
TransportMaps/Algorithms/DeepLazyMaps/__init__.py
TransportMaps/Algorithms/SequentialInference/LinearSequentialInference.py
TransportMaps/Algorithms/SequentialInference/NonLinearSequentialInference.py
TransportMaps/Algorithms/SequentialInference/SequentialInferenceBase.py
TransportMaps/Algorithms/SequentialInference/__init__.py
TransportMaps/Algorithms/SparsityIdentification/GeneralizedPrecision.py
TransportMaps/Algorithms/SparsityIdentification/NodeOrdering.py
TransportMaps/Algorithms/SparsityIdentification/RegularizedMap.py
TransportMaps/Algorithms/SparsityIdentification/SparsityIdentificationNonGaussian.py
TransportMaps/Algorithms/SparsityIdentification/__init__.py
TransportMaps/Builders/BuilderBase.py
TransportMaps/Builders/__init__.py
TransportMaps/CLI/AdaptivityPostprocessBase.py
TransportMaps/CLI/AvailableOptions.py
TransportMaps/CLI/ConstructionScriptBase.py
TransportMaps/CLI/DeepLazyMapsConstructionScriptBase.py
TransportMaps/CLI/PostprocessBase.py
TransportMaps/CLI/ScriptBase.py
TransportMaps/CLI/SequentialPostprocessBase.py
TransportMaps/CLI/__init__.py
TransportMaps/CLI/_utils.py
TransportMaps/CLI/cli_tmap_laplace.py
TransportMaps/CLI/cli_tmap_postprocess.py
TransportMaps/CLI/cli_tmap_sampling.py
TransportMaps/CLI/cli_tmap_tm.py
TransportMaps/DOLFIN/SolverBase.py
TransportMaps/DOLFIN/__init__.py
transportmaps-3.1.1.dist-info/licenses/COPYING
transportmaps-3.1.1.dist-info/licenses/COPYING.LESSER
transportmaps-3.1.1.dist-info/METADATA
transportmaps-3.1.1.dist-info/WHEEL
transportmaps-3.1.1.dist-info/entry_points.txt
transportmaps-3.1.1.dist-info/top_level.txt
transportmaps-3.1.1.dist-info/zip-safe
transportmaps-3.1.1.dist-info/RECORD
