Metadata-Version: 2.4
Name: transportmaps
Version: 3.1.1
Summary: Tools for the construction of transport maps
Author-email: Daniele Bigoni <dabi@limitcycle.it>
License: LGPL
Classifier: Development Status :: 4 - Beta
Classifier: Intended Audience :: Science/Research
Classifier: License :: OSI Approved :: GNU Lesser General Public License v3 (LGPLv3)
Classifier: Natural Language :: English
Classifier: Operating System :: POSIX
Classifier: Operating System :: POSIX :: Linux
Classifier: Operating System :: Unix
Classifier: Operating System :: MacOS
Classifier: Programming Language :: Python
Classifier: Topic :: Scientific/Engineering
Classifier: Topic :: Scientific/Engineering :: Mathematics
Classifier: Topic :: Scientific/Engineering :: Artificial Intelligence
Requires-Python: >=3.8
License-File: COPYING
License-File: COPYING.LESSER
Requires-Dist: click
Requires-Dist: numpy>=2.0
Requires-Dist: SpectralToolbox>=3.1.0
Requires-Dist: scipy
Requires-Dist: scikit-learn
Requires-Dist: sortedcontainers
Requires-Dist: semilattices>=1.0
Requires-Dist: tqdm
Requires-Dist: fasteners
Requires-Dist: h5py
Requires-Dist: matplotlib
Requires-Dist: statsmodels
Provides-Extra: dolfin
Requires-Dist: dolfin; extra == "dolfin"
Requires-Dist: dolfin_adjoint; extra == "dolfin"
Requires-Dist: petsc4py; extra == "dolfin"
Provides-Extra: suitesparse
Requires-Dist: scikit-sparse; extra == "suitesparse"
Provides-Extra: hmc
Requires-Dist: pyhmc; extra == "hmc"
Dynamic: license-file
